welvet/__init__.py
welvet/utils.py
welvet/android_arm64/libloom.so
welvet/linux_arm64/libloom.so
welvet/linux_x86_64/libloom.so
welvet/macos_arm64/libloom.dylib
welvet/macos_universal/libloom.dylib
welvet/macos_x86_64/libloom.dylib
welvet/windows_arm64/libloom.dll
welvet/windows_x86_64/libloom.dll
welvet-0.0.10.dist-info/METADATA
welvet-0.0.10.dist-info/WHEEL
welvet-0.0.10.dist-info/top_level.txt
welvet-0.0.10.dist-info/RECORD
