Metadata-Version: 2.4
Name: welvet
Version: 0.0.10
Summary: High-Performance AI Engine (Loom v0.0.8) — Native WebGPU, Transformer Inference, and 100% Determinism
Author: OpenFluke / Samuel Watson
License: Apache-2.0
Project-URL: Homepage, https://github.com/openfluke/loom
Project-URL: Source, https://github.com/openfluke/loom
Project-URL: Issues, https://github.com/openfluke/loom/issues
Project-URL: Documentation, https://github.com/openfluke/loom/tree/main/python
Keywords: neural-network,webgpu,gpu,deep-learning,transformer,swiglu,moe,safetensors,wasm,determinism
Classifier: Programming Language :: Python :: 3
Classifier: Programming Language :: Python :: 3.8
Classifier: Programming Language :: Python :: 3.9
Classifier: Programming Language :: Python :: 3.10
Classifier: Programming Language :: Python :: 3.11
Classifier: Programming Language :: Python :: 3.12
Classifier: Programming Language :: Python :: Implementation :: CPython
Classifier: Operating System :: OS Independent
Classifier: Topic :: Scientific/Engineering :: Artificial Intelligence
Classifier: Topic :: Software Development :: Libraries :: Python Modules
Requires-Python: >=3.8
